boinor/__init__.py
boinor/bodies.py
boinor/ephem.py
boinor/examples.py
boinor/io.py
boinor/maneuver.py
boinor/sensors.py
boinor/spheroid_location.py
boinor/util.py
boinor/warnings.py
boinor/_math/__init__.py
boinor/_math/integrate.py
boinor/_math/interpolate.py
boinor/_math/ivp.py
boinor/_math/linalg.py
boinor/_math/optimize.py
boinor/_math/special.py
boinor/constants/__init__.py
boinor/constants/general.py
boinor/constants/mean_elements.py
boinor/constants/rotational_elements.py
boinor/core/__init__.py
boinor/core/angles.py
boinor/core/czml_utils.py
boinor/core/elements.py
boinor/core/events.py
boinor/core/fixed.py
boinor/core/flybys.py
boinor/core/iod.py
boinor/core/maneuver.py
boinor/core/perturbations.py
boinor/core/sensors.py
boinor/core/spheroid_location.py
boinor/core/util.py
boinor/core/earth_atmosphere/__init__.py
boinor/core/earth_atmosphere/jacchia.py
boinor/core/earth_atmosphere/util.py
boinor/core/propagation/__init__.py
boinor/core/propagation/base.py
boinor/core/propagation/cowell.py
boinor/core/propagation/danby.py
boinor/core/propagation/farnocchia.py
boinor/core/propagation/gooding.py
boinor/core/propagation/markley.py
boinor/core/propagation/mikkola.py
boinor/core/propagation/pimienta.py
boinor/core/propagation/recseries.py
boinor/core/propagation/vallado.py
boinor/core/threebody/__init__.py
boinor/core/threebody/cr3bp_quantities_calculations.py
boinor/core/thrust/__init__.py
boinor/core/thrust/change_a_inc.py
boinor/core/thrust/change_argp.py
boinor/core/thrust/change_ecc_inc.py
boinor/core/thrust/change_ecc_quasioptimal.py
boinor/czml/__init__.py
boinor/czml/extract_czml.py
boinor/earth/__init__.py
boinor/earth/enums.py
boinor/earth/util.py
boinor/earth/atmosphere/__init__.py
boinor/earth/atmosphere/base.py
boinor/earth/atmosphere/coesa62.py
boinor/earth/atmosphere/coesa76.py
boinor/earth/atmosphere/jacchia.py
boinor/earth/atmosphere/data/coesa62.dat
boinor/earth/atmosphere/data/coesa76.dat
boinor/earth/atmosphere/data/coesa76_p.dat
boinor-0.19.0.dist-info/licenses/COPYING
boinor-0.19.0.dist-info/WHEEL
boinor-0.19.0.dist-info/METADATA
boinor-0.19.0.dist-info/RECORD
