Metadata-Version: 2.4
Name: boinor
Version: 0.19.0
Summary: Utilities and Python wrappers for Orbital Mechanics.
Keywords: aero,aerospace,engineering,astrodynamics,orbits,kepler,orbital mechanics
Author-email: Thorsten Alteholz <boinor@alteholz.dev>
Maintainer-email: Thorsten Alteholz <boinor@alteholz.dev>
Requires-Python: >=3.10
Classifier: License :: OSI Approved :: MIT License
Classifier: Development Status :: 4 - Beta
Classifier: Intended Audience :: Education
Classifier: Intended Audience :: Science/Research
Classifier: License :: OSI Approved :: MIT License
Classifier: Operating System :: OS Independent
Classifier: Programming Language :: Python
Classifier: Programming Language :: Python :: 3
Classifier: Programming Language :: Python :: 3.10
Classifier: Programming Language :: Python :: 3.11
Classifier: Programming Language :: Python :: 3.12
Classifier: Programming Language :: Python :: 3.13
Classifier: Programming Language :: Python :: Implementation :: CPython
Classifier: Topic :: Scientific/Engineering
Classifier: Topic :: Scientific/Engineering :: Physics
Classifier: Topic :: Scientific/Engineering :: Astronomy
License-File: COPYING
Requires-Dist: astropy >=6.1
Requires-Dist: astroquery >=0.3.9
Requires-Dist: jplephem
Requires-Dist: matplotlib >=2.0,!=3.0.1
Requires-Dist: numba >=0.61.0 ; python_version>='3.10'
Requires-Dist: numpy >= 2.0.2
Requires-Dist: pandas
Requires-Dist: plotly >=4.0,<6
Requires-Dist: pyerfa
Requires-Dist: scipy >=1.4.0
Requires-Dist: czml3 ~=0.5.3 ; extra == "cesium"
Requires-Dist: httpx ; extra == "doc"
Requires-Dist: ipython>=5.0 ; extra == "doc"
Requires-Dist: ipywidgets>=7.6 ; extra == "doc"
Requires-Dist: jupyter-client ; extra == "doc"
Requires-Dist: jupytext ; extra == "doc"
Requires-Dist: jupyter ; extra == "doc"
Requires-Dist: myst-parser ; extra == "doc"
Requires-Dist: nbsphinx>=0.8.6 ; extra == "doc"
Requires-Dist: nbconvert>=5.5 ; extra == "doc"
Requires-Dist: sgp4 ; extra == "doc"
Requires-Dist: sphinx<8.0 ; extra == "doc"
Requires-Dist: sphinx-autoapi ; extra == "doc"
Requires-Dist: sphinx-gallery<=0.7.0 ; extra == "doc"
Requires-Dist: sphinx_rtd_theme ; extra == "doc"
Requires-Dist: sphinx-hoverxref ; extra == "doc"
Requires-Dist: sphinx-notfound-page ; extra == "doc"
Requires-Dist: sphinx-copybutton ; extra == "doc"
Requires-Dist: sphinx-github-role ; extra == "doc"
Requires-Dist: sphinxcontrib-bibtex ; extra == "doc"
Requires-Dist: notebook ; extra == "jupyter"
Requires-Dist: ipywidgets>=7.6 ; extra == "jupyter"
Requires-Dist: coverage ; extra == "test"
Requires-Dist: hypothesis ; extra == "test"
Requires-Dist: import-linter[toml] ; extra == "test"
Requires-Dist: interrogate ; extra == "test"
Requires-Dist: mypy>=0.740 ; extra == "test"
Requires-Dist: pre-commit ; extra == "test"
Requires-Dist: pytest>=3.2 ; extra == "test"
Requires-Dist: pytest-cov<2.6.0 ; extra == "test"
Requires-Dist: pytest-doctestplus>=0.8 ; extra == "test"
Requires-Dist: pytest-mpl ; extra == "test"
Requires-Dist: pytest-mypy ; extra == "test"
Requires-Dist: pytest-remotedata ; extra == "test"
Requires-Dist: pytest-xdist[psutil] ; extra == "test"
Requires-Dist: pytest-timestamps ; extra == "test"
Requires-Dist: tox ; extra == "test"
Requires-Dist: vulture ; extra == "test"
Project-URL: Changelog, https://docs.boinor.space/en/stable/changelog.html
Project-URL: Documentation, https://docs.boinor.space
Project-URL: Funding, https://opencollective.com/boinor
Project-URL: Homepage, https://www.boinor.space
Project-URL: Source, https://github.com/boinor/boinor
Project-URL: Tracker, https://github.com/boinor/boinor/issues
Provides-Extra: cesium
Provides-Extra: doc
Provides-Extra: jupyter
Provides-Extra: test
